livekit/plugins/talklabs/__init__.py
livekit/plugins/talklabs/py.typed
livekit/plugins/talklabs/stt.py
livekit/plugins/talklabs/tts.py
livekit/plugins/talklabs/version.py
livekit_plugins_talklabs-2.0.2.dist-info/licenses/LICENSE
livekit_plugins_talklabs-2.0.2.dist-info/METADATA
livekit_plugins_talklabs-2.0.2.dist-info/WHEEL
livekit_plugins_talklabs-2.0.2.dist-info/top_level.txt
livekit_plugins_talklabs-2.0.2.dist-info/RECORD
