Metadata-Version: 2.4
Name: livekit-plugins-talklabs
Version: 2.0.2
Summary: TalkLabs TTS and STT plugin for LiveKit Agents
Author-email: TalkLabs <support@talklabs.com.br>
License: MIT
Project-URL: Homepage, https://github.com/talklabs/livekit-plugins-talklabs
Project-URL: Documentation, https://docs.talklabs.com.br
Project-URL: Repository, https://github.com/talklabs/livekit-plugins-talklabs
Project-URL: Issues, https://github.com/talklabs/livekit-plugins-talklabs/issues
Keywords: livekit,webrtc,realtime,tts,text-to-speech,stt,speech-to-text,talklabs,portuguese
Classifier: Development Status :: 4 - Beta
Classifier: Intended Audience :: Developers
Classifier: Topic :: Software Development :: Libraries :: Python Modules
Classifier: Topic :: Multimedia :: Sound/Audio :: Speech
Classifier: License :: OSI Approved :: MIT License
Classifier: Programming Language :: Python :: 3
Classifier: Programming Language :: Python :: 3.9
Classifier: Programming Language :: Python :: 3.10
Classifier: Programming Language :: Python :: 3.11
Classifier: Programming Language :: Python :: 3.12
Classifier: Operating System :: OS Independent
Requires-Python: >=3.9
License-File: LICENSE
Requires-Dist: livekit-agents>=1.2.0
Requires-Dist: talklabs>=2.0.2
Requires-Dist: talklabs-stt>=2.0.2
Requires-Dist: websockets>=15.0
Provides-Extra: dev
Requires-Dist: pytest>=8.0.0; extra == "dev"
Requires-Dist: pytest-asyncio>=0.23.0; extra == "dev"
Requires-Dist: pytest-cov>=4.1.0; extra == "dev"
Requires-Dist: pytest-mock>=3.12.0; extra == "dev"
Requires-Dist: pytest-timeout>=2.2.0; extra == "dev"
Requires-Dist: black>=24.0.0; extra == "dev"
Requires-Dist: pylint>=3.0.0; extra == "dev"
Requires-Dist: mypy>=1.8.0; extra == "dev"
Requires-Dist: flake8>=7.0.0; extra == "dev"
Requires-Dist: build>=1.0.0; extra == "dev"
Requires-Dist: twine>=5.0.0; extra == "dev"
Dynamic: license-file
